perturbopy/__init__.py
perturbopy/conftest.py
perturbopy/setup.cfg
perturbopy/tests_use.py
perturbopy/generate_input/__init__.py
perturbopy/generate_input/generate_input.py
perturbopy/io_utils/__init__.py
perturbopy/io_utils/io.py
perturbopy/postproc/__init__.py
perturbopy/postproc/calc_modes/__init__.py
perturbopy/postproc/calc_modes/bands.py
perturbopy/postproc/calc_modes/calc_mode.py
perturbopy/postproc/calc_modes/dyna_indiv_run.py
perturbopy/postproc/calc_modes/dyna_pp.py
perturbopy/postproc/calc_modes/dyna_run.py
perturbopy/postproc/calc_modes/ephmat.py
perturbopy/postproc/calc_modes/ephmat_spin.py
perturbopy/postproc/calc_modes/imsigma.py
perturbopy/postproc/calc_modes/imsigma_spin.py
perturbopy/postproc/calc_modes/phdisp.py
perturbopy/postproc/calc_modes/spectral_cumulant.py
perturbopy/postproc/calc_modes/spins.py
perturbopy/postproc/calc_modes/trans.py
perturbopy/postproc/dbs/__init__.py
perturbopy/postproc/dbs/recip_pt_db.py
perturbopy/postproc/dbs/units_dict.py
perturbopy/postproc/utils/__init__.py
perturbopy/postproc/utils/constants.py
perturbopy/postproc/utils/lattice.py
perturbopy/postproc/utils/memory.py
perturbopy/postproc/utils/plot_tools.py
perturbopy/postproc/utils/spectra_generate_pulse.py
perturbopy/postproc/utils/spectra_plots.py
perturbopy/postproc/utils/spectra_trans_abs.py
perturbopy/postproc/utils/timing.py
perturbopy/test_utils/__init__.py
perturbopy/test_utils/compare_data/__init__.py
perturbopy/test_utils/compare_data/compare.py
perturbopy/test_utils/compare_data/h5.py
perturbopy/test_utils/compare_data/yaml.py
perturbopy/test_utils/legacy/legacy.py
perturbopy/test_utils/run_test/__init__.py
perturbopy/test_utils/run_test/env_utils.py
perturbopy/test_utils/run_test/run_utils.py
perturbopy/test_utils/run_test/test_driver.py
perturbopy/testing_code/__init__.py
perturbopy/testing_code/test_functions.py
perturbopy/yml_files/files_description.yml
perturbopy/yml_files/input_parameters_perturbo.yml
perturbopy-0.7.2.dist-info/licenses/LICENSE
perturbopy-0.7.2.dist-info/METADATA
perturbopy-0.7.2.dist-info/WHEEL
perturbopy-0.7.2.dist-info/entry_points.txt
perturbopy-0.7.2.dist-info/top_level.txt
perturbopy-0.7.2.dist-info/RECORD
