Metadata-Version: 2.4
Name: perturbopy
Version: 0.7.2
Summary: Suite of Python scripts for Perturbo testing and postprocessing
Requires-Python: >=3.7.12
License-File: LICENSE
Requires-Dist: numpy>=1.21.4
Requires-Dist: pytest
Requires-Dist: pytest-order
Requires-Dist: h5py
Requires-Dist: PyYAML
Requires-Dist: pytest-profiling
Requires-Dist: matplotlib>=2.2.0
Requires-Dist: scipy
Provides-Extra: interactive
Requires-Dist: jupyter; extra == "interactive"
Requires-Dist: pytest-plt; extra == "interactive"
Dynamic: license-file
Dynamic: requires-python
